celeste_mistral/__init__.py
celeste_mistral/py.typed
celeste_mistral/chat/__init__.py
celeste_mistral/chat/client.py
celeste_mistral/chat/config.py
celeste_mistral/chat/parameters.py
celeste_mistral/chat/streaming.py
celeste_mistral-0.3.6.dist-info/METADATA
celeste_mistral-0.3.6.dist-info/WHEEL
celeste_mistral-0.3.6.dist-info/RECORD
